bedrock_protocol/binarystream/__init__.py
bedrock_protocol/binarystream/binary_stream.py
bedrock_protocol/binarystream/read_only_binary_stream.py
bedrock_protocol/binarystream/_internal/__init__.py
bedrock_protocol/binarystream/_internal/native_library.py
bedrock_protocol/binarystream/_internal/arm64/BinaryStream.dll
bedrock_protocol/binarystream/_internal/arm64/libBinaryStream.dylib
bedrock_protocol/binarystream/_internal/arm64/libBinaryStream.so
bedrock_protocol/binarystream/_internal/x86_64/BinaryStream.dll
bedrock_protocol/binarystream/_internal/x86_64/libBinaryStream.dylib
bedrock_protocol/binarystream/_internal/x86_64/libBinaryStream.so
bedrock_protocol_binarystream-1.4.0.dist-info/licenses/LICENSE
tests/test.py
bedrock_protocol_binarystream-1.4.0.dist-info/METADATA
bedrock_protocol_binarystream-1.4.0.dist-info/WHEEL
bedrock_protocol_binarystream-1.4.0.dist-info/top_level.txt
bedrock_protocol_binarystream-1.4.0.dist-info/RECORD
