Metadata-Version: 2.4
Name: bedrock-protocol-binarystream
Version: 1.4.0
Summary: Minecraft BinaryStream Library
Author: GlacieTeam
License: MPL-2.0
Project-URL: homepage, https://github.com/GlacieTeam/bedrock-protocol-binarystream
Classifier: Programming Language :: Python :: 3
Classifier: License :: OSI Approved :: Mozilla Public License 2.0 (MPL 2.0)
Classifier: Operating System :: OS Independent
Requires-Python: >=3
License-File: LICENSE
Dynamic: license-file
